[
    {"source":"Londres",
     "targets":[

       {
           "target":"Hong Kong",
           "distance":9617,
           "value":1770000
       },

        {
            "target":"Macau",
            "distance":9591,
            "value":70000
        },
        {
            "target":"Tokio",
            "distance":9553,
            "value":900000
        }
     ]
    },
    {

        "source":"Shenzhen",
        "targets":[

            {
                "target":"San Andres",
                "distance":15739,
                "value":900000
            },
            {
                "target":"Mecca",
                "distance":7561,
                "value":700200
            },
            {
                "target":"New York",
                "distance":12924,
                "value":1873100
            }
        ]
    },
    {
      "source":"Singapur",
      "targets":[
          {
              "target":"Taipei",
              "distance":3245,
              "value":100000
          },
          {
              "target":"Londres",
              "distance":10841,
              "value":122000
          },
          {
              "target":"Tokio",
              "distance":5308,
              "value":355000
          }
      ]
  },
  {
        "source":"Paris",
        "targets":[
            {
                "target":"New York",
                "distance":4151,
                "value":80000
            },
            {
                "target":"Dubai",
                "distance":6800,
                "value":200000
            },
            {
                "target":"Hong Kong",
                "distance":9620,
                "value":120000
            },
        ]
    },
    {
        "source":"Taipei",
        "targets":[

            {
                "target":"Macau",
                "distance":875,
                "value":580000
            },
            {
                "target":"singapur",
                "distance":3245,
                "value":9830000
            },
            {
                "target":"San andres",
                "distance":15121,
                "value":124000
            }
        ]
    }
]
